pybioportal/__aux_funcs.py
pybioportal/__config.py
pybioportal/__init__.py
pybioportal/cancer_types.py
pybioportal/clinical_attributes.py
pybioportal/clinical_data.py
pybioportal/copy_number_segment.py
pybioportal/discrete_copy_number_alterations.py
pybioportal/gene_panel_data.py
pybioportal/gene_panels.py
pybioportal/generic_assay_data.py
pybioportal/generic_assays.py
pybioportal/genes.py
pybioportal/info.py
pybioportal/molecular_data.py
pybioportal/molecular_profiles.py
pybioportal/mutations.py
pybioportal/patients.py
pybioportal/sample_lists.py
pybioportal/samples.py
pybioportal/server_running_status.py
pybioportal/studies.py
pybioportal/treatments.py
pybioportal-1.0.1.dist-info/LICENSE.txt
pybioportal-1.0.1.dist-info/METADATA
pybioportal-1.0.1.dist-info/WHEEL
pybioportal-1.0.1.dist-info/top_level.txt
pybioportal-1.0.1.dist-info/RECORD
