Metadata-Version: 2.1
Name: pybioportal
Version: 1.0.1
Summary: A Python package to easily retrieve data from cBioPortal
Author-email: Matteo Valerio <mv.datascientist@outlook.com>
License: BSD 3-Clause License
Project-URL: homepage, https://github.com/Matteo-Valerio/pyBioPortal
Project-URL: documentation, https://pybioportal.readthedocs.io
Project-URL: repository, https://github.com/Matteo-Valerio/pyBioPortal
Keywords: cBioPortal,bioinformatics,data science,cancer
Classifier: Programming Language :: Python :: 3
Classifier: License :: OSI Approved :: BSD License
Classifier: Operating System :: OS Independent
Requires-Python: >=3.9
License-File: LICENSE.txt
Requires-Dist: requests >=2.28.0
Requires-Dist: pandas >=1.5.0
Requires-Dist: numpy >=1.22.0
